xdyn.cpython-39-x86_64-linux-gnu.so
xdyn-6.4.1.dist-info/WHEEL
xdyn-6.4.1.dist-info/top_level.txt
xdyn-6.4.1.dist-info/METADATA
xdyn-6.4.1.dist-info/RECORD
